OpsApi/__init__.py
OpsApi/tm.py
OpsApi-1.1.3.dist-info/LICENSE
OpsApi-1.1.3.dist-info/METADATA
OpsApi-1.1.3.dist-info/WHEEL
OpsApi-1.1.3.dist-info/top_level.txt
OpsApi-1.1.3.dist-info/RECORD
