Metadata-Version: 2.1
Name: OpsApi
Version: 1.1.3
Summary: OpsApi package
Author-email: Tommi <xm6798121@gmail.com>
Classifier: Programming Language :: Python :: 3
Classifier: License :: OSI Approved :: MIT License
Classifier: Operating System :: OS Independent
Requires-Python: >=3.7
License-File: LICENSE
Requires-Dist: requests
